py_atmosphere/__init__.py
py_atmosphere/mach_number.py
py_atmosphere/py_atmosphere.py
py_atmosphere/temp_conversion.py
py_atmosphere_mach-0.3.7.dist-info/LICENSE
py_atmosphere_mach-0.3.7.dist-info/METADATA
py_atmosphere_mach-0.3.7.dist-info/WHEEL
py_atmosphere_mach-0.3.7.dist-info/RECORD
