Metadata-Version: 2.3
Name: py_atmosphere_mach
Version: 0.3.7
Summary: Calculate standard air properties given altitude input in specific units!
License: MIT
Author: Tianjiao Jiang, Zhengling Jiang, Francisco Ramirez
Requires-Python: >=3.9,<4.0
Classifier: License :: OSI Approved :: MIT License
Classifier: Programming Language :: Python :: 3
Classifier: Programming Language :: Python :: 3.9
Classifier: Programming Language :: Python :: 3.10
Classifier: Programming Language :: Python :: 3.11
Classifier: Programming Language :: Python :: 3.12
Classifier: Programming Language :: Python :: 3.13
